Excel_modify/__init__.py
Excel_modify/edit_excel.py
Excel_modify/edit_main_comment.py
Excel_modify/edit_share_comment.py
Excel_modify/excel_mode.py
Excel_modify/dll/DrCinco.dll
excel_modify-2.0.dist-info/METADATA
excel_modify-2.0.dist-info/WHEEL
excel_modify-2.0.dist-info/top_level.txt
excel_modify-2.0.dist-info/RECORD
