Metadata-Version: 2.1
Name: excel_modify
Version: 2.0
Summary: A package for editing Excel files for specific files
Home-page: https://github.com/DrCinco730/excel_modifier
Author: DrCino
Author-email: khaled775057605@gmail.com
Requires-Dist: beautifulsoup4
